faraday_cli/__init__.py
faraday_cli/config.py
faraday_cli/api_client/__init__.py
faraday_cli/api_client/exceptions.py
faraday_cli/api_client/faraday_api.py
faraday_cli/api_client/filter.py
faraday_cli/api_client/resources.py
faraday_cli/extras/__init__.py
faraday_cli/extras/halo/__init__.py
faraday_cli/extras/halo/_utils.py
faraday_cli/extras/halo/cursor.py
faraday_cli/extras/halo/halo.py
faraday_cli/extras/termgraph/__init__.py
faraday_cli/extras/termgraph/termgraph.py
faraday_cli/shell/__init__.py
faraday_cli/shell/exceptions.py
faraday_cli/shell/main.py
faraday_cli/shell/shell.py
faraday_cli/shell/utils.py
faraday_cli/shell/modules/__init__.py
faraday_cli/shell/modules/agent.py
faraday_cli/shell/modules/executive_report.py
faraday_cli/shell/modules/host.py
faraday_cli/shell/modules/reports.py
faraday_cli/shell/modules/service.py
faraday_cli/shell/modules/stats.py
faraday_cli/shell/modules/tools.py
faraday_cli/shell/modules/vulnerability.py
faraday_cli/shell/modules/workspace.py
faraday_cli-2.2.1.dist-info/licenses/LICENSE
faraday_cli-2.2.1.dist-info/METADATA
faraday_cli-2.2.1.dist-info/WHEEL
faraday_cli-2.2.1.dist-info/entry_points.txt
faraday_cli-2.2.1.dist-info/top_level.txt
faraday_cli-2.2.1.dist-info/RECORD
