Metadata-Version: 2.4
Name: faraday-cli
Version: 2.2.1
Summary: Faraday cli package
Home-page: https://github.com/infobyte/faraday-cli
Author: Faradaysec
Author-email: devel@faradaysec.com
License: GNU General Public License v3
Classifier: Development Status :: 4 - Beta
Classifier: Intended Audience :: Developers
Classifier: License :: OSI Approved :: GNU General Public License v3 (GPLv3)
Classifier: Natural Language :: English
Classifier: Programming Language :: Python :: 3
Classifier: Programming Language :: Python :: 3.7
Classifier: Programming Language :: Python :: 3.8
Requires-Python: >3.7.0
License-File: LICENSE
Requires-Dist: faraday-plugins>=1.26.0
Requires-Dist: click>=8.0.1
Requires-Dist: colorama>=0.4.4
Requires-Dist: jsonschema>=3.2.0
Requires-Dist: PyYAML>=5.4.1
Requires-Dist: simple-rest-client>=1.0.8
Requires-Dist: tabulate>=0.8.9
Requires-Dist: validators<=0.20.0,>=0.18.2
Requires-Dist: spinners>=0.0.24
Requires-Dist: termcolor>=1.1.0
Requires-Dist: cmd2<3.0.0,>=2.3.0
Requires-Dist: log-symbols>=0.0.14
Requires-Dist: arrow>=1.1.0
Requires-Dist: py-sneakers>=1.0.1
Requires-Dist: luddite>=1.0.2
Requires-Dist: packaging>=21.3
Requires-Dist: httpx<=0.28
Provides-Extra: dev
Requires-Dist: giteasychangelog; extra == "dev"
Requires-Dist: flake8; extra == "dev"
Requires-Dist: black; extra == "dev"
Requires-Dist: pre-commit; extra == "dev"
Provides-Extra: test
Requires-Dist: pytest; extra == "test"
Requires-Dist: pytest-cov; extra == "test"
Requires-Dist: faradaysec; extra == "test"
Provides-Extra: docs
Requires-Dist: mkdocs; extra == "docs"
Requires-Dist: mkdocs-material; extra == "docs"
Dynamic: author
Dynamic: author-email
Dynamic: classifier
Dynamic: description
Dynamic: description-content-type
Dynamic: home-page
Dynamic: license
Dynamic: license-file
Dynamic: provides-extra
Dynamic: requires-dist
Dynamic: requires-python
Dynamic: summary
